xcm/__init__.py
xcm/mc.py
xcm-0.1.0.dist-info/METADATA
xcm-0.1.0.dist-info/WHEEL
xcm-0.1.0.dist-info/entry_points.txt
xcm-0.1.0.dist-info/top_level.txt
xcm-0.1.0.dist-info/RECORD
