Metadata-Version: 2.1
Name: xcm
Version: 0.1.0
Summary: A command line tool to perform custom tasks.
Home-page: https://github.com/yourusername/mycommand
Author: Mouxiao Huang
Author-email: huangmouxiao@gmail.com
Classifier: Programming Language :: Python :: 3
Classifier: License :: OSI Approved :: MIT License
Classifier: Operating System :: OS Independent
Requires-Python: >=3.6
